hivipy/JON.py
hivipy/JON_sup.py
hivipy/PDUtil.py
hivipy/SQLAUtil.py
hivipy/__init__.py
hivipy/arrays.py
hivipy/communication.py
hivipy/confUtils.py
hivipy/config.py
hivipy/crud.py
hivipy/crudstruct_forms.py
hivipy/crypto.py
hivipy/db.py
hivipy/error.py
hivipy/file.py
hivipy/form.py
hivipy/hivi_init.py
hivipy/interfaces.py
hivipy/lang_datas.py
hivipy/nosql.py
hivipy/objects.py
hivipy/pd_crud.py
hivipy/schemas.py
hivipy/sql.py
hivipy/sqlcrud-old.py
hivipy/sqlcrud.py
hivipy/string.py
hivipy/template.py
hivipy/utils.py
hivipy/xml_file.py
hivipy-0.0.1.dist-info/METADATA
hivipy-0.0.1.dist-info/WHEEL
hivipy-0.0.1.dist-info/top_level.txt
hivipy-0.0.1.dist-info/RECORD
