Metadata-Version: 2.1
Name: hivipy
Version: 0.0.1
Summary: Package accelerateur de developpement sur python à l'aide de FLASK
Author: BILONG NTOUBA Célestin
Author-email: bilongntouba.celestin@gmail.com
Keywords: python,flask,headless-cms,package
Requires-Dist: jonschema ; python_version >= "0.0.2"
Requires-Dist: Flask-IPFilter ; python_version >= "0.0.5"
Requires-Dist: pdoc3 ; python_version >= "0.10.0"
Requires-Dist: xmltodict ; python_version >= "0.13.0"
Requires-Dist: pygeoip ; python_version >= "0.3.2"
Requires-Dist: sqlalchemy-utils ; python_version >= "0.38.3"
Requires-Dist: Flask-Session ; python_version >= "0.4.0"
Requires-Dist: Flask-WeasyPrint ; python_version >= "0.6"
Requires-Dist: pyexcel-xlsx ; python_version >= "0.6.0"
Requires-Dist: pyexcel-xls ; python_version >= "0.7.0"
Requires-Dist: google-currency ; python_version >= "1.0.10"
Requires-Dist: pymysql ; python_version >= "1.0.2"
Requires-Dist: python-datauri ; python_version >= "1.1.0"
Requires-Dist: flask-ipban ; python_version >= "1.1.5"
Requires-Dist: pg8000 ; python_version >= "1.29.1"
Requires-Dist: pandas ; python_version >= "1.4.3"
Requires-Dist: SQLAlchemy ; python_version >= "1.4.39"
Requires-Dist: alembic ; python_version >= "1.8.0"
Requires-Dist: Flask[async] ; python_version >= "2.1.2"
Requires-Dist: Flask-Limiter ; python_version >= "2.4.6"
Requires-Dist: vulture ; python_version >= "2.5"
Requires-Dist: python-dateutil ; python_version >= "2.8.2"
Requires-Dist: pytz ; python_version >= "2022.1"
Requires-Dist: Flask-Cors ; python_version >= "3.0.10"
Requires-Dist: openpyxl ; python_version >= "3.0.10"
Requires-Dist: Jinja2 ; python_version >= "3.1.2"
Requires-Dist: pycryptodome ; python_version >= "3.15.0"
Requires-Dist: asyncio ; python_version >= "3.4.3"
Requires-Dist: typing ; python_version >= "3.7.4.3"
Requires-Dist: pymongo ; python_version >= "4.2.0"
Requires-Dist: tinydb ; python_version >= "4.7.0"
Requires-Dist: configparser ; python_version >= "5.2.0"
Requires-Dist: weasyprint ; python_version >= "55.0"
Requires-Dist: twilio ; python_version >= "7.16.0"
Requires-Dist: qrcode ; python_version >= "7.3.1"
